pycompliance/__init__.py
pycompliance/pycompliance.py
pycompliance/tests/__init__.py
pycompliance/tests/test.py
pycompliance-0.0.1.dist-info/METADATA
pycompliance-0.0.1.dist-info/WHEEL
pycompliance-0.0.1.dist-info/licenses/LICENSE
pycompliance-0.0.1.dist-info/RECORD
