Metadata-Version: 2.1
Name: pycompliance
Version: 0.0.1
Summary: Library for working with compliance benchmarks and data.
Project-URL: Homepage, https://github.com/rhmdnd/pycompliance
Project-URL: Bug Tracker, https://github.com/rhmdnd/pycompliance/issues
License-File: LICENSE
Classifier: License :: OSI Approved :: Apache Software License
Classifier: Operating System :: OS Independent
Classifier: Programming Language :: Python :: 3
Requires-Python: >=3.7
